Workbook

Sheet Welcome!
A12: Tax Deductions - Individual
A18: Got questions? Contact us on wegotyou@theaccountingacademy.com.au
B22: © 2025 The Accounting Academy. All rights reserved.
B23: This workpaper is for educational use only and may not be copied, reproduced, or distributed without written permission.

Sheet Instructions
A1: Instructions
A3: 1 | B3: Complete every section of this workbook
A4: 2 | B4: Do not update the Income and Expenses worksheet. This feeds in from the other sheets
A5: 3 | B5: If you have to calculate anything, please enter the detail to the relevant worksheet
A6: 4 | B6: Ensure you have copies of all invoices and receipts
A7: 5 | B7: Please reference each invoice/receipt in the relevant worksheet
A16: Navigation
A17: Next

Sheet Client Details
A1: Tax Deductions
A3: Client Name: | C3: Year Ending:
A6: Client Address
A8: P6. Client Address:
A11: Client Details
A12: Occupation
A13: Date of Birth
A14: Does the client have a spouse?
A15: Is the client exempt from Medicare - Medicare Entitlement Statement
A16: Does the client have private health?
A17: Current Super Balance
A20: Deductions Client is Claiming
A21: Motor Vehicle?
A22: Travel?
... A52: No

Sheet Expenses
A1: Personal Expenses
A3: Expenses | C3: Amount | D3: Label
A4: Work-related Car Expenses | C4: ='D1. Work-related Car Expenses'!C14+'D1. Work-related Car Expenses'!C19 | D4: D1
A5: Work-related travel expenses | C5: ='D2. Work-related travel expense'!C17 | D5: D2
A6: Work-related clothing, laundry and dry cleaning expenses | C6: ='D3. Work-related clothing'!C17 | D6: D3
A7: Work-related self-education expenses | C7: ='D4. Self-education'!C17 | D7: D4
A8: Other work-related expenses | C8: ='D5. Other work-related expenses'!C17 | D8: D5
A9: Depreciable expenses | C9: ='D5. Depreciable expenses'!H23 | D9: D5 - Depreciation
A10: Low value pool deduction | C10: ='D6. Low value pool deduction'!G23 | D10: D6
A11: Interest deductions | C11: ='D7. Interest deductions'!C17 | D11: D7
A12: Dividend deductions | C12: ='D8. Dividend deductions'!C17 | D12: D8
A13: Gifts or donations | C13: ='D9. Gifts or donations'!C17 | D13: D9
A14: Cost of managing tax affairs | C14: ='D10. Cost of managing tax affai'!C17 | D14: D10
A15: Deductible amount of UPP of foreign pension or annuity | C15: ='D11. UPP of foreign pension or '!C17 | D15: D11
A16: Personal superannuation contributions | C16: ='D12. Personal superannuation co'!C17 | D16: D12
A17: Deduction for project pool | C17: ='D13. Deduction for project pool'!C17 | D17: D13
A18: Forestry managed investment scheme deduction | C18: ='D14. Forestry managed investmen'!C17 | D18: D14
A19: Other deductions | C19: ='D15. Other deductions'!C17 | D19: D15
A20: Tax losses of earlier income year | C20: ='L1. Tax losses of earlier incom'!C17 | D20: L1
A21: Total Expenses | C21: =SUM(C4:C20)
A25: Navigation
A26: Next

Sheet D1. Work-related Car Expenses
A1: D1. Work-related Car Expenses
A3: Full Cost
A4: Expense | C4: Amount | D4: Reference
A12: Total Expenses | C12: =SUM(C5:C11)
A13: Logbook Percentage (%)
A14: Total Deduction | C14: =C12*C13
A16: Mileage
A17: Number of Km's | B17: Cents Per Km | C17: Amount | D17: Reference
C18: =A18*B18
A19: Total | C19: =C18
A22: Navigation
A23: Next
A24: Home

Sheet D2. Work-related travel expense
A1: D2. Work-related travel expenses
A3: Expense | C3: Amount | D3: Reference
A17: Total | C17: =SUM(C4:C16)
A20: Navigation
A21: Next
A22: Home

Sheet D3. Work-related clothing
A1: D3. Work-related clothing, laundry and dry cleaning expenses
A3: Expense | C3: Amount | D3: Reference
A17: Total | C17: =SUM(C4:C16)
A20: Navigation
A21: Next
A22: Home

Sheet D4. Self-education
A1: D4. Work-related self-education expenses
A3: Expense | C3: Amount | D3: Reference
A17: Total | C17: =SUM(C4:C16)
A20: Navigation
A21: Next
A22: Home

Sheet D5. Other work-related expenses
A1: D5. Other work-related expenses
A3: Expense | C3: Amount | D3: Reference
A17: Total | C17: =SUM(C4:C16)
A20: Navigation
A21: Next
A22: Home

Sheet D5. Depreciable expenses
A1: D5. Depreciable expenses
A2: Depreciation Schedule
A4: New Assets
A5: Date Purchased | B5: Description | C5: Purchase Amount | D5: Opening Amount | E5: Accumulated Depreciation | F5: Useful Life | G5: Depreciation Method | H5: Depreciation Expense | I5: Closing Balance | J5: Invoice
E6: =C6-D6 | H6: =IFERROR(IF(G6=$A$51,D6*IF(('Client Details'!$D$3-'D5. Depreciable expenses'!A6)<365,('Client Details'!$D$3-'D5. Depreciable expenses'!A6+1)/365,1)*(2/'D5. Depreciable expenses'!F6),('D5. Depreciable expenses'!C6/'D5. Depreciable expenses'!F6)*IF(('Client Details'!$D$3-'D5. Depreciable expenses'!A6)<365,('Client Details'!$D$3-'D5. Depreciable expenses'!A6+1)/365,1)),0) | I6: =D6-H6
E7: =C7-D7 | H7: =IFERROR(IF(G7=$A$51,D7*IF(('Client Details'!$D$3-'D5. Depreciable expenses'!A7)<365,('Client Details'!$D$3-'D5. Depreciable expenses'!A7+1)/365,1)*(2/'D5. Depreciable expenses'!F7),('D5. Depreciable expenses'!C7/'D5. Depreciable expenses'!F7)*IF(('Client Details'!$D$3-'D5. Depreciable expenses'!A7)<365,('Client Details'!$D$3-'D5. Depreciable expenses'!A7+1)/365,1)),0) | I7: =D7-H7
E8: =C8-D8 | H8: =IFERROR(IF(G8=$A$51,D8*IF(('Client Details'!$D$3-'D5. Depreciable expenses'!A8)<365,('Client Details'!$D$3-'D5. Depreciable expenses'!A8+1)/365,1)*(2/'D5. Depreciable expenses'!F8),('D5. Depreciable expenses'!C8/'D5. Depreciable expenses'!F8)*IF(('Client Details'!$D$3-'D5. Depreciable expenses'!A8)<365,('Client Details'!$D$3-'D5. Depreciable expenses'!A8+1)/365,1)),0) | I8: =D8-H8
E9: =C9-D9 | H9: =IFERROR(IF(G9=$A$51,D9*IF(('Client Details'!$D$3-'D5. Depreciable expenses'!A9)<365,('Client Details'!$D$3-'D5. Depreciable expenses'!A9+1)/365,1)*(2/'D5. Depreciable expenses'!F9),('D5. Depreciable expenses'!C9/'D5. Depreciable expenses'!F9)*IF(('Client Details'!$D$3-'D5. Depreciable expenses'!A9)<365,('Client Details'!$D$3-'D5. Depreciable expenses'!A9+1)/365,1)),0) | I9: =D9-H9
E10: =C10-D10 | H10: =IFERROR(IF(G10=$A$51,D10*IF(('Client Details'!$D$3-'D5. Depreciable expenses'!A10)<365,('Client Details'!$D$3-'D5. Depreciable expenses'!A10+1)/365,1)*(2/'D5. Depreciable expenses'!F10),('D5. Depreciable expenses'!C10/'D5. Depreciable expenses'!F10)*IF(('Client Details'!$D$3-'D5. Depreciable expenses'!A10)<365,('Client Details'!$D$3-'D5. Depreciable expenses'!A10+1)/365,1)),0) | I10: =D10-H10
E11: =C11-D11 | H11: =IFERROR(IF(G11=$A$51,D11*IF(('Client Details'!$D$3-'D5. Depreciable expenses'!A11)<365,('Client Details'!$D$3-'D5. Depreciable expenses'!A11+1)/365,1)*(2/'D5. Depreciable expenses'!F11),('D5. Depreciable expenses'!C11/'D5. Depreciable expenses'!F11)*IF(('Client Details'!$D$3-'D5. Depreciable expenses'!A11)<365,('Client Details'!$D$3-'D5. Depreciable expenses'!A11+1)/365,1)),0) | I11: =D11-H11
E12: =C12-D12 | H12: =IFERROR(IF(G12=$A$51,D12*IF(('Client Details'!$D$3-'D5. Depreciable expenses'!A12)<365,('Client Details'!$D$3-'D5. Depreciable expenses'!A12+1)/365,1)*(2/'D5. Depreciable expenses'!F12),('D5. Depreciable expenses'!C12/'D5. Depreciable expenses'!F12)*IF(('Client Details'!$D$3-'D5. Depreciable expenses'!A12)<365,('Client Details'!$D$3-'D5. Depreciable expenses'!A12+1)/365,1)),0) | I12: =D12-H12
E13: =C13-D13 | H13: =IFERROR(IF(G13=$A$51,D13*IF(('Client Details'!$D$3-'D5. Depreciable expenses'!A13)<365,('Client Details'!$D$3-'D5. Depreciable expenses'!A13+1)/365,1)*(2/'D5. Depreciable expenses'!F13),('D5. Depreciable expenses'!C13/'D5. Depreciable expenses'!F13)*IF(('Client Details'!$D$3-'D5. Depreciable expenses'!A13)<365,('Client Details'!$D$3-'D5. Depreciable expenses'!A13+1)/365,1)),0) | I13: =D13-H13
E14: =C14-D14 | H14: =IFERROR(IF(G14=$A$51,D14*IF(('Client Details'!$D$3-'D5. Depreciable expenses'!A14)<365,('Client Details'!$D$3-'D5. Depreciable expenses'!A14+1)/365,1)*(2/'D5. Depreciable expenses'!F14),('D5. Depreciable expenses'!C14/'D5. Depreciable expenses'!F14)*IF(('Client Details'!$D$3-'D5. Depreciable expenses'!A14)<365,('Client Details'!$D$3-'D5. Depreciable expenses'!A14+1)/365,1)),0) | I14: =D14-H14
E15: =C15-D15 | H15: =IFERROR(IF(G15=$A$51,D15*IF(('Client Details'!$D$3-'D5. Depreciable expenses'!A15)<365,('Client Details'!$D$3-'D5. Depreciable expenses'!A15+1)/365,1)*(2/'D5. Depreciable expenses'!F15),('D5. Depreciable expenses'!C15/'D5. Depreciable expenses'!F15)*IF(('Client Details'!$D$3-'D5. Depreciable expenses'!A15)<365,('Client Details'!$D$3-'D5. Depreciable expenses'!A15+1)/365,1)),0) | I15: =D15-H15
E16: =C16-D16 | H16: =IFERROR(IF(G16=$A$51,D16*IF(('Client Details'!$D$3-'D5. Depreciable expenses'!A16)<365,('Client Details'!$D$3-'D5. Depreciable expenses'!A16+1)/365,1)*(2/'D5. Depreciable expenses'!F16),('D5. Depreciable expenses'!C16/'D5. Depreciable expenses'!F16)*IF(('Client Details'!$D$3-'D5. Depreciable expenses'!A16)<365,('Client Details'!$D$3-'D5. Depreciable expenses'!A16+1)/365,1)),0) | I16: =D16-H16
E17: =C17-D17 | H17: =IFERROR(IF(G17=$A$51,D17*IF(('Client Details'!$D$3-'D5. Depreciable expenses'!A17)<365,('Client Details'!$D$3-'D5. Depreciable expenses'!A17+1)/365,1)*(2/'D5. Depreciable expenses'!F17),('D5. Depreciable expenses'!C17/'D5. Depreciable expenses'!F17)*IF(('Client Details'!$D$3-'D5. Depreciable expenses'!A17)<365,('Client Details'!$D$3-'D5. Depreciable expenses'!A17+1)/365,1)),0) | I17: =D17-H17
... E22: =C22-D22 | H22: =IFERROR(IF(G22=$A$51,D22*IF(('Client Details'!$D$3-'D5. Depreciable expenses'!A22)<365,('Client Details'!$D$3-'D5. Depreciable expenses'!A22+1)/365,1)*(2/'D5. Depreciable expenses'!F22),('D5. Depreciable expenses'!C22/'D5. Depreciable expenses'!F22)*IF(('Client Details'!$D$3-'D5. Depreciable expenses'!A22)<365,('Client Details'!$D$3-'D5. Depreciable expenses'!A22+1)/365,1)),0) | I22: =D22-H22
A23: Total | C23: =SUM(C6:C22) | D23: =SUM(D6:D22) | E23: =SUM(E6:E22) | H23: =SUM(H6:H22) | I23: =SUM(I6:I22)
A26: Navigation
A27: Next
A28: Home
A48: Don't Delete
A50: Straight Line
A51: Diminishing Value

Sheet D6. Low value pool deduction
A1: D6. Low Value Pool
A4: New Assets
A5: Date Purchased | B5: Description | C5: Purchase Amount | D5: Opening Amount | E5: Accumulated Depreciation | F5: Depreciation Method | G5: Depreciation Expense | H5: Closing Balance
E6: =C6-D6 | G6: =IF(AND(F6="Low Value Asset", ('Client Details'!$D$3 - A6) < 365), "Use Low Cost", IF(OR(F6="Low Value Asset", F6<>"Low Cost Asset"), D6*0.375, D6*IF(('Client Details'!$D$3 - A6)<365, 0.1875, 0.375))) | H6: =D6-G6
E7: =C7-D7 | G7: =IF(AND(F7="Low Value Asset", ('Client Details'!$D$3 - A7) < 365), "Use Low Cost", IF(OR(F7="Low Value Asset", F7<>"Low Cost Asset"), D7*0.375, D7*IF(('Client Details'!$D$3 - A7)<365, 0.1875, 0.375))) | H7: =D7-G7
E8: =C8-D8 | G8: =IF(AND(F8="Low Value Asset", ('Client Details'!$D$3 - A8) < 365), "Use Low Cost", IF(OR(F8="Low Value Asset", F8<>"Low Cost Asset"), D8*0.375, D8*IF(('Client Details'!$D$3 - A8)<365, 0.1875, 0.375))) | H8: =D8-G8
E9: =C9-D9 | G9: =IF(AND(F9="Low Value Asset", ('Client Details'!$D$3 - A9) < 365), "Use Low Cost", IF(OR(F9="Low Value Asset", F9<>"Low Cost Asset"), D9*0.375, D9*IF(('Client Details'!$D$3 - A9)<365, 0.1875, 0.375))) | H9: =D9-G9
E10: =C10-D10 | G10: =IF(AND(F10="Low Value Asset", ('Client Details'!$D$3 - A10) < 365), "Use Low Cost", IF(OR(F10="Low Value Asset", F10<>"Low Cost Asset"), D10*0.375, D10*IF(('Client Details'!$D$3 - A10)<365, 0.1875, 0.375))) | H10: =D10-G10
E11: =C11-D11 | G11: =IF(AND(F11="Low Value Asset", ('Client Details'!$D$3 - A11) < 365), "Use Low Cost", IF(OR(F11="Low Value Asset", F11<>"Low Cost Asset"), D11*0.375, D11*IF(('Client Details'!$D$3 - A11)<365, 0.1875, 0.375))) | H11: =D11-G11
E12: =C12-D12 | G12: =IF(AND(F12="Low Value Asset", ('Client Details'!$D$3 - A12) < 365), "Use Low Cost", IF(OR(F12="Low Value Asset", F12<>"Low Cost Asset"), D12*0.375, D12*IF(('Client Details'!$D$3 - A12)<365, 0.1875, 0.375))) | H12: =D12-G12
E13: =C13-D13 | G13: =IF(AND(F13="Low Value Asset", ('Client Details'!$D$3 - A13) < 365), "Use Low Cost", IF(OR(F13="Low Value Asset", F13<>"Low Cost Asset"), D13*0.375, D13*IF(('Client Details'!$D$3 - A13)<365, 0.1875, 0.375))) | H13: =D13-G13
E14: =C14-D14 | G14: =IF(AND(F14="Low Value Asset", ('Client Details'!$D$3 - A14) < 365), "Use Low Cost", IF(OR(F14="Low Value Asset", F14<>"Low Cost Asset"), D14*0.375, D14*IF(('Client Details'!$D$3 - A14)<365, 0.1875, 0.375))) | H14: =D14-G14
E15: =C15-D15 | G15: =IF(AND(F15="Low Value Asset", ('Client Details'!$D$3 - A15) < 365), "Use Low Cost", IF(OR(F15="Low Value Asset", F15<>"Low Cost Asset"), D15*0.375, D15*IF(('Client Details'!$D$3 - A15)<365, 0.1875, 0.375))) | H15: =D15-G15
E16: =C16-D16 | G16: =IF(AND(F16="Low Value Asset", ('Client Details'!$D$3 - A16) < 365), "Use Low Cost", IF(OR(F16="Low Value Asset", F16<>"Low Cost Asset"), D16*0.375, D16*IF(('Client Details'!$D$3 - A16)<365, 0.1875, 0.375))) | H16: =D16-G16
E17: =C17-D17 | G17: =IF(AND(F17="Low Value Asset", ('Client Details'!$D$3 - A17) < 365), "Use Low Cost", IF(OR(F17="Low Value Asset", F17<>"Low Cost Asset"), D17*0.375, D17*IF(('Client Details'!$D$3 - A17)<365, 0.1875, 0.375))) | H17: =D17-G17
... E22: =C22-D22 | G22: =IF(AND(F22="Low Value Asset", ('Client Details'!$D$3 - A22) < 365), "Use Low Cost", IF(OR(F22="Low Value Asset", F22<>"Low Cost Asset"), D22*0.375, D22*IF(('Client Details'!$D$3 - A22)<365, 0.1875, 0.375))) | H22: =D22-G22
A23: Total | C23: =SUM(C6:C22) | D23: =SUM(D6:D22) | E23: =SUM(E6:E22) | G23: =SUM(G6:G22) | H23: =SUM(H6:H22)
A26: Navigation
A27: Next
A28: Home
A48: Don't Delete
A50: Low Cost Asset
A51: Low Value Asset

Sheet D7. Interest deductions
A1: D7. Interest deductions
A3: Expense | C3: Amount | D3: Reference
A17: Total | C17: =SUM(C4:C16)
A20: Navigation
A21: Next
A22: Home

Sheet D8. Dividend deductions
A1: D8. Dividend deductions
A3: Expense | C3: Amount | D3: Reference
A17: Total | C17: =SUM(C4:C16)
A20: Navigation
A21: Next
A22: Home

Sheet D9. Gifts or donations
A1: D9. Gifts or donations
A3: Expense | C3: Amount | D3: Reference
A17: Total | C17: =SUM(C4:C16)
A20: Navigation
A21: Next
A22: Home

Sheet D10. Cost of managing tax affai
A1: D10. Cost of managing tax affairs
A3: Expense | C3: Amount | D3: Reference
A17: Total | C17: =SUM(C4:C16)
A20: Navigation
A21: Next
A22: Home

Sheet D11. UPP of foreign pension or 
A1: D11. Deductible amount of UPP of foreign pension or annuity
A3: Expense | C3: Amount | D3: Reference
A17: Total | C17: =SUM(C4:C16)
A20: Navigation
A21: Next
A22: Home

Sheet D12. Personal superannuation co
A1: D12. Personal superannuation contributions
A3: Expense | C3: Amount | D3: Reference
A17: Total | C17: =SUM(C4:C16)
A20: Navigation
A21: Next
A22: Home

Sheet D13. Deduction for project pool
A1: D13. Deduction for project pool
A3: Expense | C3: Amount | D3: Reference
A17: Total | C17: =SUM(C4:C16)
A20: Navigation
A21: Next
A22: Home

Sheet D14. Forestry managed investmen
A1: D14. Forestry managed investment scheme deduction
A3: Expense | C3: Amount | D3: Reference
A17: Total | C17: =SUM(C4:C16)
A20: Navigation
A21: Next
A22: Home

Sheet D15. Other deductions
A1: D15. Other deductions
A3: Expense | C3: Amount | D3: Reference
A17: Total | C17: =SUM(C4:C16)
A20: Navigation
A21: Next
A22: Home

Sheet L1. Tax losses of earlier incom
A1: L1. Tax losses of earlier income year
A3: Expense | C3: Amount | D3: Reference
A17: Total | C17: =SUM(C4:C16)
A20: Navigation
A21: Next
A22: Home

Sheet Sheet2
